[{"iob":1.805,"activity":0.0139,"bolussnooze":1.174,"basaliob":0.173,"netbasalinsulin":0.6,"hightempinsulin":0.7,"time":"2016-10-10T19:59:41.000Z"},{"iob":1.732,"activity":0.0147,"bolussnooze":0.979,"basaliob":0.15,"netbasalinsulin":0.6,"hightempinsulin":0.7,"time":"2016-10-10T20:04:41.000Z"},{"iob":1.653,"activity":0.0157,"bolussnooze":0.796,"basaliob":0.129,"netbasalinsulin":0.55,"hightempinsulin":0.65,"time":"2016-10-10T20:09:41.000Z"},{"iob":1.57,"activity":0.0167,"bolussnooze":0.631,"basaliob":0.11,"netbasalinsulin":0.55,"hightempinsulin":0.65,"time":"2016-10-10T20:14:41.000Z"},{"iob":1.482,"activity":0.0176,"bolussnooze":0.485,"basaliob":0.092,"netbasalinsulin":0.55,"hightempinsulin":0.65,"time":"2016-10-10T20:19:41.000Z"},{"iob":1.389,"activity":0.0186,"bolussnooze":0.359,"basaliob":0.077,"netbasalinsulin":0.55,"hightempinsulin":0.65,"time":"2016-10-10T20:24:41.000Z"},{"iob":1.291,"activity":0.0196,"bolussnooze":0.251,"basaliob":0.063,"netbasalinsulin":0.55,"hightempinsulin":0.65,"time":"2016-10-10T20:29:41.000Z"},{"iob":1.188,"activity":0.0206,"bolussnooze":0.163,"basaliob":0.051,"netbasalinsulin":0.55,"hightempinsulin":0.65,"time":"2016-10-10T20:34:41.000Z"},{"iob":1.08,"activity":0.0216,"bolussnooze":0.094,"basaliob":0.04,"netbasalinsulin":0.5,"hightempinsulin":0.6,"time":"2016-10-10T20:39:41.000Z"},{"iob":0.972,"activity":0.0213,"bolussnooze":0.043,"basaliob":0.031,"netbasalinsulin":0.5,"hightempinsulin":0.6,"time":"2016-10-10T20:44:41.000Z"},{"iob":0.872,"activity":0.0201,"bolussnooze":0.012,"basaliob":0.023,"netbasalinsulin":0.45,"hightempinsulin":0.55,"time":"2016-10-10T20:49:41.000Z"},{"iob":0.778,"activity":0.0189,"bolussnooze":0,"basaliob":0.016,"netbasalinsulin":0.4,"hightempinsulin":0.5,"time":"2016-10-10T20:54:41.000Z"},{"iob":0.689,"activity":0.0177,"bolussnooze":0,"basaliob":0.01,"netbasalinsulin":0.4,"hightempinsulin":0.5,"time":"2016-10-10T20:59:41.000Z"},{"iob":0.607,"activity":0.0165,"bolussnooze":0,"basaliob":0.006,"netbasalinsulin":0.4,"hightempinsulin":0.5,"time":"2016-10-10T21:04:41.000Z"},{"iob":0.53,"activity":0.0154,"bolussnooze":0,"basaliob":0.002,"netbasalinsulin":0.4,"hightempinsulin":0.5,"time":"2016-10-10T21:09:41.000Z"},{"iob":0.458,"activity":0.0142,"bolussnooze":0,"basaliob":-0.001,"netbasalinsulin":0.35,"hightempinsulin":0.45,"time":"2016-10-10T21:14:41.000Z"},{"iob":0.393,"activity":0.0131,"bolussnooze":0,"basaliob":-0.002,"netbasalinsulin":0.3,"hightempinsulin":0.4,"time":"2016-10-10T21:19:41.000Z"},{"iob":0.333,"activity":0.012,"bolussnooze":0,"basaliob":-0.004,"netbasalinsulin":0.2,"hightempinsulin":0.3,"time":"2016-10-10T21:24:41.000Z"},{"iob":0.278,"activity":0.011,"bolussnooze":0,"basaliob":-0.004,"netbasalinsulin":0.15,"hightempinsulin":0.25,"time":"2016-10-10T21:29:41.000Z"},{"iob":0.228,"activity":0.0099,"bolussnooze":0,"basaliob":-0.004,"netbasalinsulin":0.2,"hightempinsulin":0.25,"time":"2016-10-10T21:34:41.000Z"},{"iob":0.184,"activity":0.0089,"bolussnooze":0,"basaliob":-0.004,"netbasalinsulin":0.2,"hightempinsulin":0.25,"time":"2016-10-10T21:39:41.000Z"},{"iob":0.144,"activity":0.0079,"bolussnooze":0,"basaliob":-0.003,"netbasalinsulin":0.1,"hightempinsulin":0.15,"time":"2016-10-10T21:44:41.000Z"},{"iob":0.11,"activity":0.0069,"bolussnooze":0,"basaliob":-0.002,"netbasalinsulin":0,"hightempinsulin":0.05,"time":"2016-10-10T21:49:41.000Z"},{"iob":0.08,"activity":0.0059,"bolussnooze":0,"basaliob":-0.002,"netbasalinsulin":-0.05,"hightempinsulin":0,"time":"2016-10-10T21:54:41.000Z"},{"iob":0.055,"activity":0.005,"bolussnooze":0,"basaliob":-0.001,"netbasalinsulin":-0.05,"hightempinsulin":0,"time":"2016-10-10T21:59:41.000Z"},{"iob":0.035,"activity":0.0041,"bolussnooze":0,"basaliob":-0.001,"netbasalinsulin":-0.05,"hightempinsulin":0,"time":"2016-10-10T22:04:41.000Z"},{"iob":0.019,"activity":0.0032,"bolussnooze":0,"basaliob":0,"netbasalinsulin":-0.05,"hightempinsulin":0,"time":"2016-10-10T22:09:41.000Z"},{"iob":0.008,"activity":0.0022,"bolussnooze":0,"basaliob":0,"netbasalinsulin":-0.05,"hightempinsulin":0,"time":"2016-10-10T22:14:41.000Z"},{"iob":0.001,"activity":0.0013,"bolussnooze":0,"basaliob":0,"netbasalinsulin":-0.05,"hightempinsulin":0,"time":"2016-10-10T22:19:41.000Z"},{"iob":0,"activity":0.0004,"bolussnooze":0,"basaliob":0,"netbasalinsulin":0,"hightempinsulin":0,"time":"2016-10-10T22:24:41.000Z"},{"iob":0,"activity":0,"bolussnooze":0,"basaliob":0,"netbasalinsulin":0,"hightempinsulin":0,"time":"2016-10-10T22:29:41.000Z"},{"iob":0,"activity":0,"bolussnooze":0,"basaliob":0,"netbasalinsulin":0,"hightempinsulin":0,"time":"2016-10-10T22:34:41.000Z"},{"iob":0,"activity":0,"bolussnooze":0,"basaliob":0,"netbasalinsulin":0,"hightempinsulin":0,"time":"2016-10-10T22:39:41.000Z"},{"iob":0,"activity":0,"bolussnooze":0,"basaliob":0,"netbasalinsulin":0,"hightempinsulin":0,"time":"2016-10-10T22:44:41.000Z"},{"iob":0,"activity":0,"bolussnooze":0,"basaliob":0,"netbasalinsulin":0,"hightempinsulin":0,"time":"2016-10-10T22:49:41.000Z"},{"iob":0,"activity":0,"bolussnooze":0,"basaliob":0,"netbasalinsulin":0,"hightempinsulin":0,"time":"2016-10-10T22:54:41.000Z"},{"iob":0,"activity":0,"bolussnooze":0,"basaliob":0,"netbasalinsulin":0,"hightempinsulin":0,"time":"2016-10-10T22:59:41.000Z"},{"iob":0,"activity":0,"bolussnooze":0,"basaliob":0,"netbasalinsulin":0,"hightempinsulin":0,"time":"2016-10-10T23:04:41.000Z"},{"iob":0,"activity":0,"bolussnooze":0,"basaliob":0,"netbasalinsulin":0,"hightempinsulin":0,"time":"2016-10-10T23:09:41.000Z"},{"iob":0,"activity":0,"bolussnooze":0,"basaliob":0,"netbasalinsulin":0,"hightempinsulin":0,"time":"2016-10-10T23:14:41.000Z"},{"iob":0,"activity":0,"bolussnooze":0,"basaliob":0,"netbasalinsulin":0,"hightempinsulin":0,"time":"2016-10-10T23:19:41.000Z"},{"iob":0,"activity":0,"bolussnooze":0,"basaliob":0,"netbasalinsulin":0,"hightempinsulin":0,"time":"2016-10-10T23:24:41.000Z"}]
