[{"iob":-0.235,"activity":0,"bolussnooze":0,"basaliob":-0.235,"netbasalinsulin":0.05,"hightempinsulin":0.55,"time":"2016-10-16T19:49:21.000Z"},{"iob":-0.233,"activity":-0.0005,"bolussnooze":0,"basaliob":-0.233,"netbasalinsulin":-0.05,"hightempinsulin":0.45,"time":"2016-10-16T19:54:21.000Z"},{"iob":-0.228,"activity":-0.0009,"bolussnooze":0,"basaliob":-0.228,"netbasalinsulin":-0.1,"hightempinsulin":0.4,"time":"2016-10-16T19:59:21.000Z"},{"iob":-0.222,"activity":-0.0013,"bolussnooze":0,"basaliob":-0.222,"netbasalinsulin":-0.2,"hightempinsulin":0.3,"time":"2016-10-16T20:04:21.000Z"},{"iob":-0.214,"activity":-0.0016,"bolussnooze":0,"basaliob":-0.214,"netbasalinsulin":-0.25,"hightempinsulin":0.25,"time":"2016-10-16T20:09:21.000Z"},{"iob":-0.205,"activity":-0.0019,"bolussnooze":0,"basaliob":-0.205,"netbasalinsulin":-0.3,"hightempinsulin":0.2,"time":"2016-10-16T20:14:21.000Z"},{"iob":-0.194,"activity":-0.0021,"bolussnooze":0,"basaliob":-0.194,"netbasalinsulin":-0.3,"hightempinsulin":0.2,"time":"2016-10-16T20:19:21.000Z"},{"iob":-0.183,"activity":-0.0023,"bolussnooze":0,"basaliob":-0.183,"netbasalinsulin":-0.3,"hightempinsulin":0.2,"time":"2016-10-16T20:24:21.000Z"},{"iob":-0.171,"activity":-0.0024,"bolussnooze":0,"basaliob":-0.171,"netbasalinsulin":-0.3,"hightempinsulin":0.2,"time":"2016-10-16T20:29:21.000Z"},{"iob":-0.158,"activity":-0.0025,"bolussnooze":0,"basaliob":-0.158,"netbasalinsulin":-0.25,"hightempinsulin":0.2,"time":"2016-10-16T20:34:21.000Z"},{"iob":-0.146,"activity":-0.0025,"bolussnooze":0,"basaliob":-0.146,"netbasalinsulin":-0.2,"hightempinsulin":0.2,"time":"2016-10-16T20:39:21.000Z"},{"iob":-0.133,"activity":-0.0025,"bolussnooze":0,"basaliob":-0.133,"netbasalinsulin":-0.15,"hightempinsulin":0.2,"time":"2016-10-16T20:44:21.000Z"},{"iob":-0.121,"activity":-0.0025,"bolussnooze":0,"basaliob":-0.121,"netbasalinsulin":-0.15,"hightempinsulin":0.2,"time":"2016-10-16T20:49:21.000Z"},{"iob":-0.109,"activity":-0.0024,"bolussnooze":0,"basaliob":-0.109,"netbasalinsulin":-0.15,"hightempinsulin":0.2,"time":"2016-10-16T20:54:21.000Z"},{"iob":-0.097,"activity":-0.0023,"bolussnooze":0,"basaliob":-0.097,"netbasalinsulin":-0.15,"hightempinsulin":0.2,"time":"2016-10-16T20:59:21.000Z"},{"iob":-0.086,"activity":-0.0022,"bolussnooze":0,"basaliob":-0.086,"netbasalinsulin":-0.15,"hightempinsulin":0.2,"time":"2016-10-16T21:04:21.000Z"},{"iob":-0.075,"activity":-0.0021,"bolussnooze":0,"basaliob":-0.075,"netbasalinsulin":-0.15,"hightempinsulin":0.2,"time":"2016-10-16T21:09:21.000Z"},{"iob":-0.065,"activity":-0.002,"bolussnooze":0,"basaliob":-0.065,"netbasalinsulin":-0.2,"hightempinsulin":0.15,"time":"2016-10-16T21:14:21.000Z"},{"iob":-0.055,"activity":-0.0019,"bolussnooze":0,"basaliob":-0.055,"netbasalinsulin":-0.2,"hightempinsulin":0.15,"time":"2016-10-16T21:19:21.000Z"},{"iob":-0.046,"activity":-0.0018,"bolussnooze":0,"basaliob":-0.046,"netbasalinsulin":-0.25,"hightempinsulin":0.1,"time":"2016-10-16T21:24:21.000Z"},{"iob":-0.038,"activity":-0.0017,"bolussnooze":0,"basaliob":-0.038,"netbasalinsulin":-0.3,"hightempinsulin":0.05,"time":"2016-10-16T21:29:21.000Z"},{"iob":-0.03,"activity":-0.0015,"bolussnooze":0,"basaliob":-0.03,"netbasalinsulin":-0.3,"hightempinsulin":0.05,"time":"2016-10-16T21:34:21.000Z"},{"iob":-0.023,"activity":-0.0014,"bolussnooze":0,"basaliob":-0.023,"netbasalinsulin":-0.35,"hightempinsulin":0,"time":"2016-10-16T21:39:21.000Z"},{"iob":-0.018,"activity":-0.0012,"bolussnooze":0,"basaliob":-0.018,"netbasalinsulin":-0.35,"hightempinsulin":0,"time":"2016-10-16T21:44:21.000Z"},{"iob":-0.013,"activity":-0.001,"bolussnooze":0,"basaliob":-0.013,"netbasalinsulin":-0.35,"hightempinsulin":0,"time":"2016-10-16T21:49:21.000Z"},{"iob":-0.009,"activity":-0.0008,"bolussnooze":0,"basaliob":-0.009,"netbasalinsulin":-0.35,"hightempinsulin":0,"time":"2016-10-16T21:54:21.000Z"},{"iob":-0.005,"activity":-0.0006,"bolussnooze":0,"basaliob":-0.005,"netbasalinsulin":-0.3,"hightempinsulin":0,"time":"2016-10-16T21:59:21.000Z"},{"iob":-0.003,"activity":-0.0005,"bolussnooze":0,"basaliob":-0.003,"netbasalinsulin":-0.3,"hightempinsulin":0,"time":"2016-10-16T22:04:21.000Z"},{"iob":-0.002,"activity":-0.0003,"bolussnooze":0,"basaliob":-0.002,"netbasalinsulin":-0.25,"hightempinsulin":0,"time":"2016-10-16T22:09:21.000Z"},{"iob":-0.001,"activity":-0.0002,"bolussnooze":0,"basaliob":-0.001,"netbasalinsulin":-0.2,"hightempinsulin":0,"time":"2016-10-16T22:14:21.000Z"},{"iob":0,"activity":-0.0001,"bolussnooze":0,"basaliob":0,"netbasalinsulin":-0.15,"hightempinsulin":0,"time":"2016-10-16T22:19:21.000Z"},{"iob":0,"activity":0,"bolussnooze":0,"basaliob":0,"netbasalinsulin":-0.1,"hightempinsulin":0,"time":"2016-10-16T22:24:21.000Z"},{"iob":0,"activity":0,"bolussnooze":0,"basaliob":0,"netbasalinsulin":-0.05,"hightempinsulin":0,"time":"2016-10-16T22:29:21.000Z"},{"iob":0,"activity":0,"bolussnooze":0,"basaliob":0,"netbasalinsulin":0,"hightempinsulin":0,"time":"2016-10-16T22:34:21.000Z"},{"iob":0,"activity":0,"bolussnooze":0,"basaliob":0,"netbasalinsulin":0,"hightempinsulin":0,"time":"2016-10-16T22:39:21.000Z"},{"iob":0,"activity":0,"bolussnooze":0,"basaliob":0,"netbasalinsulin":0,"hightempinsulin":0,"time":"2016-10-16T22:44:21.000Z"},{"iob":0,"activity":0,"bolussnooze":0,"basaliob":0,"netbasalinsulin":0,"hightempinsulin":0,"time":"2016-10-16T22:49:21.000Z"},{"iob":0,"activity":0,"bolussnooze":0,"basaliob":0,"netbasalinsulin":0,"hightempinsulin":0,"time":"2016-10-16T22:54:21.000Z"},{"iob":0,"activity":0,"bolussnooze":0,"basaliob":0,"netbasalinsulin":0,"hightempinsulin":0,"time":"2016-10-16T22:59:21.000Z"},{"iob":0,"activity":0,"bolussnooze":0,"basaliob":0,"netbasalinsulin":0,"hightempinsulin":0,"time":"2016-10-16T23:04:21.000Z"},{"iob":0,"activity":0,"bolussnooze":0,"basaliob":0,"netbasalinsulin":0,"hightempinsulin":0,"time":"2016-10-16T23:09:21.000Z"},{"iob":0,"activity":0,"bolussnooze":0,"basaliob":0,"netbasalinsulin":0,"hightempinsulin":0,"time":"2016-10-16T23:14:21.000Z"}]
