{
  "bg": 82, 
  "temp": "absolute", 
  "snoozeBG": 71, 
  "predBGs": {
    "aCOB": [
      82, 
      87, 
      93, 
      98, 
      102, 
      107, 
      111, 
      115, 
      118, 
      121, 
      123, 
      125, 
      126, 
      127
    ], 
    "IOB": [
      82, 
      78, 
      75, 
      72, 
      69, 
      68, 
      66, 
      65, 
      64, 
      63, 
      63, 
      63, 
      62
    ]
  }, 
  "rate": 0, 
  "reason": "COB: 16, Dev: 1, BGI: -3.09, ISF: 78, Target: 108; Eventual BG 71 < 108, setting -1.025U/hr", 
  "COB": 16, 
  "eventualBG": 71, 
  "duration": 30, 
  "tick": -4, 
  "IOB": 0.154
}