{
  "bg": 95, 
  "temp": "absolute", 
  "snoozeBG": 98, 
  "predBGs": {
    "aCOB": [
      95, 
      103, 
      111, 
      118, 
      124, 
      129, 
      134, 
      137, 
      140, 
      142, 
      143, 
      143, 
      143, 
      144, 
      144, 
      144, 
      144, 
      145, 
      145, 
      145, 
      146, 
      146, 
      146, 
      146, 
      146, 
      147
    ], 
    "IOB": [
      95, 
      94, 
      93, 
      93, 
      93, 
      93, 
      93, 
      93, 
      93, 
      93, 
      93, 
      93, 
      93, 
      94, 
      94, 
      94, 
      94, 
      95, 
      95, 
      95, 
      96, 
      96, 
      96, 
      96, 
      96, 
      97
    ]
  }, 
  "rate": 0, 
  "reason": "COB: 11, Dev: 0, BGI: -1.03, ISF: 90, Target: 115; Eventual BG 98 < 115, setting -0.1U/hr", 
  "COB": 11, 
  "eventualBG": 98, 
  "duration": 30, 
  "tick": -1, 
  "IOB": -0.037
}