{
  "bg": 108, 
  "temp": "absolute", 
  "snoozeBG": 103, 
  "predBGs": {
    "COB": [
      108, 
      107, 
      106, 
      105, 
      104, 
      104, 
      103, 
      103, 
      103, 
      103, 
      104, 
      104, 
      105, 
      105, 
      106, 
      107, 
      107, 
      108, 
      109, 
      110, 
      110, 
      111, 
      112, 
      113, 
      114, 
      114, 
      115, 
      116, 
      117, 
      117, 
      118, 
      118, 
      119, 
      119, 
      120, 
      120, 
      120, 
      120, 
      121
    ], 
    "aCOB": [
      108, 
      114, 
      119, 
      122, 
      125, 
      126, 
      126, 
      125, 
      124, 
      123, 
      122, 
      121, 
      120, 
      119, 
      119, 
      119, 
      118, 
      118, 
      118, 
      117
    ], 
    "IOB": [
      108, 
      107, 
      106, 
      105, 
      103, 
      102, 
      101, 
      100, 
      100, 
      99, 
      98, 
      97, 
      97, 
      96, 
      95, 
      95, 
      95, 
      94
    ]
  }, 
  "reason": "COB: 7, Dev: 10, BGI: -2.66, ISF: 97, Target: 114; 121-103 in range: no temp required; setting current basal of 0.6 as temp, but 26m left and 0.65 ~ req 0.6U/hr: no action required", 
  "COB": 7, 
  "eventualBG": 121, 
  "tick": -1, 
  "IOB": 0.214
}