{
  "bg": 149, 
  "temp": "absolute", 
  "snoozeBG": 111, 
  "predBGs": {
    "COB": [
      149, 
      149, 
      149, 
      148, 
      147, 
      146, 
      145, 
      143, 
      142, 
      140, 
      138, 
      137, 
      135, 
      133, 
      132, 
      130, 
      128, 
      127, 
      125, 
      124, 
      122, 
      121, 
      120, 
      119, 
      118, 
      117, 
      116, 
      116, 
      115, 
      114, 
      114, 
      113, 
      113, 
      112, 
      112, 
      112, 
      111
    ], 
    "aCOB": [
      149, 
      154, 
      159, 
      162, 
      165, 
      167, 
      168, 
      168, 
      167, 
      165, 
      163, 
      160, 
      156, 
      152, 
      148, 
      145, 
      141, 
      138, 
      134, 
      131, 
      128, 
      125, 
      123, 
      121, 
      119, 
      117, 
      116, 
      114, 
      113, 
      112, 
      111, 
      110, 
      110, 
      109, 
      109, 
      109, 
      108
    ], 
    "IOB": [
      149, 
      149, 
      148, 
      147, 
      145, 
      143, 
      141, 
      138, 
      135, 
      131, 
      127, 
      123, 
      119, 
      115, 
      111, 
      107, 
      104, 
      100, 
      97, 
      94, 
      91, 
      88, 
      86, 
      84, 
      82, 
      80, 
      78, 
      77, 
      76, 
      75, 
      74, 
      73, 
      73, 
      72, 
      72, 
      71
    ]
  }, 
  "rate": 0.425, 
  "reason": "COB: 14, Dev: 23, BGI: -3.87, ISF: 90, Target: 115; Eventual BG 111 < 115, setting 0.425U/hr", 
  "COB": 14, 
  "eventualBG": 111, 
  "duration": 30, 
  "tick": "+0", 
  "IOB": 0.766
}