[
  {
    "created_at": "2016-10-09T10:42:56.269Z", 
    "mmtune": {
      "scanDetails": [
        [
          "916.540", 
          4, 
          -97
        ], 
        [
          "916.564", 
          5, 
          -88
        ], 
        [
          "916.588", 
          5, 
          -86
        ], 
        [
          "916.612", 
          5, 
          -87
        ], 
        [
          "916.636", 
          5, 
          -87
        ], 
        [
          "916.660", 
          5, 
          -88
        ], 
        [
          "916.684", 
          5, 
          -91
        ]
      ], 
      "setFreq": 916.588, 
      "usedDefault": false, 
      "timestamp": "2016-10-09T10:39:52.000Z"
    }, 
    "pump": {
      "battery": {
        "status": "normal", 
        "voltage": 1.55
      }, 
      "status": {
        "status": "normal", 
        "timestamp": "2016-10-09T10:40:41.000Z", 
        "bolusing": false, 
        "suspended": false
      }, 
      "reservoir": 113.775, 
      "clock": "2016-10-09T03:40:26-07:00"
    }, 
    "openaps": {
      "suggested": {
        "bg": 116, 
        "temp": "absolute", 
        "snoozeBG": 102, 
        "timestamp": "2016-10-09T10:42:27.000Z", 
        "rate": 0, 
        "reason": "COB: 0, Dev: -22, BGI: 0.8, ISF: 100, Target: 121; Eventual BG 102 < 121, setting -0.25U/hr", 
        "COB": 0, 
        "eventualBG": 102, 
        "duration": 30, 
        "tick": -3, 
        "IOB": -0.084
      }, 
      "iob": {
        "netbasalinsulin": -0.3, 
        "timestamp": "2016-10-09T10:40:26.000Z", 
        "activity": -0.0016, 
        "basaliob": -0.084, 
        "hightempinsulin": 0.2, 
        "bolussnooze": 0, 
        "iob": -0.084
      }, 
      "enacted": {
        "bg": 116, 
        "temp": "absolute", 
        "snoozeBG": 102, 
        "recieved": true, 
        "predBGs": {
          "IOB": [
            116, 
            113, 
            111, 
            109, 
            107, 
            105, 
            104, 
            103, 
            102, 
            102, 
            102, 
            102, 
            103, 
            104, 
            105, 
            106, 
            107, 
            108, 
            108, 
            109, 
            110, 
            111, 
            112, 
            113, 
            114, 
            114, 
            115, 
            116, 
            116, 
            117, 
            117, 
            118, 
            118, 
            119
          ]
        }, 
        "reason": "COB: 0, Dev: -22, BGI: 0.8, ISF: 100, Target: 121; Eventual BG 102 < 121, setting -0.25U/hr", 
        "rate": 0, 
        "COB": 0, 
        "eventualBG": 102, 
        "timestamp": "2016-10-09T10:42:47.000Z", 
        "duration": 30, 
        "tick": -3, 
        "IOB": -0.084
      }
    }, 
    "uploader": {
      "battery": 100, 
      "batteryVoltage": 4377
    }, 
    "device": "openaps://indy-e1", 
    "_id": "57fa1f30a66b5aaa4beeb1b9"
  }
]