[
  {
    "created_at": "2016-10-13T00:56:04.090Z", 
    "mmtune": {
      "scanDetails": [
        [
          "916.564", 
          5, 
          -41
        ], 
        [
          "916.588", 
          5, 
          -38
        ], 
        [
          "916.612", 
          5, 
          -37
        ], 
        [
          "916.636", 
          5, 
          -37
        ], 
        [
          "916.660", 
          5, 
          -37
        ], 
        [
          "916.684", 
          5, 
          -38
        ], 
        [
          "916.708", 
          2, 
          -79
        ]
      ], 
      "setFreq": 916.66, 
      "usedDefault": false, 
      "timestamp": "2016-10-13T00:53:14.000Z"
    }, 
    "pump": {
      "battery": {
        "status": "normal", 
        "voltage": 1.36
      }, 
      "status": {
        "status": "normal", 
        "timestamp": "2016-10-13T00:53:35.000Z", 
        "bolusing": false, 
        "suspended": false
      }, 
      "reservoir": 109.25, 
      "clock": "2016-10-12T17:53:46-07:00"
    }, 
    "openaps": {
      "suggested": {
        "bg": 125, 
        "temp": "absolute", 
        "snoozeBG": 140, 
        "timestamp": "2016-10-13T00:55:34.000Z", 
        "rate": 0.975, 
        "reason": "COB: 68, Dev: 22, BGI: -6.46, ISF: 82, Target: 80; Eventual BG 141 >= 80, temp 0.675<0.975U/hr", 
        "COB": 68, 
        "eventualBG": 141, 
        "duration": 30, 
        "tick": "+1", 
        "IOB": 1.496
      }, 
      "iob": {
        "netbasalinsulin": 0.45, 
        "timestamp": "2016-10-13T00:53:46.000Z", 
        "activity": 0.0158, 
        "basaliob": 0.298, 
        "hightempinsulin": 1.25, 
        "bolussnooze": 0.94, 
        "iob": 1.496
      }, 
      "enacted": {
        "bg": 125, 
        "temp": "absolute", 
        "snoozeBG": 140, 
        "recieved": true, 
        "predBGs": {
          "COB": [
            125, 
            123, 
            120, 
            117, 
            115, 
            112, 
            109, 
            106, 
            103, 
            99, 
            96, 
            93, 
            90, 
            88, 
            86, 
            85, 
            85, 
            84, 
            84, 
            85, 
            85, 
            86, 
            87, 
            89, 
            91, 
            92, 
            94, 
            97, 
            99, 
            102, 
            104, 
            107, 
            111, 
            114, 
            117, 
            120, 
            123, 
            126, 
            129, 
            132, 
            135, 
            138, 
            141
          ], 
          "aCOB": [
            125, 
            128, 
            132, 
            134, 
            137, 
            140, 
            142, 
            144, 
            146, 
            147, 
            149, 
            150, 
            152, 
            154, 
            156, 
            159, 
            162, 
            165, 
            169, 
            173, 
            177, 
            181, 
            185, 
            189, 
            194, 
            198, 
            203, 
            207, 
            212, 
            216, 
            221, 
            226, 
            231, 
            235, 
            240, 
            244, 
            248, 
            252, 
            256, 
            260, 
            264, 
            267, 
            270
          ], 
          "IOB": [
            125, 
            122, 
            119, 
            115, 
            111, 
            107, 
            102, 
            97, 
            91, 
            86, 
            79, 
            73, 
            66, 
            60, 
            55, 
            50, 
            46, 
            42, 
            39
          ]
        }, 
        "reason": "COB: 68, Dev: 22, BGI: -6.46, ISF: 82, Target: 80; Eventual BG 141 >= 80, temp 0.675<0.975U/hr", 
        "rate": 0.975, 
        "COB": 68, 
        "eventualBG": 141, 
        "timestamp": "2016-10-13T00:55:55.000Z", 
        "duration": 30, 
        "tick": "+1", 
        "IOB": 1.496
      }
    }, 
    "uploader": {
      "battery": 52, 
      "batteryVoltage": 3702
    }, 
    "device": "openaps://indy-e1", 
    "_id": "57fedba47447f6f15f153e33"
  }
]