{
  "device": "openaps://indy-e1", 
  "pump": {
    "battery": {
      "status": "normal", 
      "voltage": 1.56
    }, 
    "status": {
      "status": "normal", 
      "timestamp": "2016-10-14T02:51:46.000Z", 
      "bolusing": false, 
      "suspended": false
    }, 
    "reservoir": 87.025, 
    "clock": "2016-10-13T19:51:58-07:00"
  }, 
  "uploader": {
    "battery": 100, 
    "batteryVoltage": 4365
  }, 
  "openaps": {
    "suggested": {
      "bg": 115, 
      "temp": "absolute", 
      "snoozeBG": 142, 
      "timestamp": "2016-10-14T02:53:20.000Z", 
      "reason": "COB: 0, Dev: 9, BGI: -2.58, ISF: 89, Target: 114; Eventual BG 142 >= 114, temp 0.85<1.2U/hr", 
      "rate": 1.2, 
      "COB": 0, 
      "eventualBG": 142, 
      "duration": 30, 
      "tick": "+2", 
      "IOB": -0.202
    }, 
    "iob": {
      "netbasalinsulin": 0.8, 
      "timestamp": "2016-10-14T02:51:58.000Z", 
      "activity": 0.0058, 
      "basaliob": -0.218, 
      "hightempinsulin": 1.4, 
      "bolussnooze": 0, 
      "iob": -0.202
    }, 
    "enacted": {
      "bg": 115, 
      "temp": "absolute", 
      "snoozeBG": 142, 
      "recieved": true, 
      "predBGs": {
        "IOB": [
          115, 
          114, 
          113, 
          113, 
          113, 
          113, 
          114, 
          115, 
          117, 
          118, 
          120, 
          121, 
          123, 
          124, 
          126, 
          127, 
          128, 
          130, 
          131, 
          132, 
          133, 
          134, 
          135, 
          136, 
          137, 
          137, 
          138, 
          138, 
          138, 
          138, 
          139
        ]
      }, 
      "rate": 1.175, 
      "reason": "COB: 0, Dev: 9, BGI: -2.58, ISF: 89, Target: 114; Eventual BG 142 >= 114, temp 0.85<1.2U/hr", 
      "COB": 0, 
      "eventualBG": 142, 
      "timestamp": "2016-10-14T02:53:44.000Z", 
      "duration": 30, 
      "tick": "+2", 
      "IOB": -0.202
    }
  }, 
  "mmtune": {
    "scanDetails": [
      [
        "916.564", 
        5, 
        -82
      ], 
      [
        "916.588", 
        5, 
        -79
      ], 
      [
        "916.612", 
        5, 
        -76
      ], 
      [
        "916.636", 
        5, 
        -76
      ], 
      [
        "916.660", 
        5, 
        -76
      ], 
      [
        "916.684", 
        5, 
        -78
      ], 
      [
        "916.708", 
        2, 
        -94
      ]
    ], 
    "setFreq": 916.66, 
    "timestamp": "2016-10-14T02:51:25.000Z", 
    "usedDefault": false
  }
}